oroio/__init__.py
oroio/__version__.py
oroio/cli.py
oroio/config.py
oroio-2.0.0.dist-info/METADATA
oroio-2.0.0.dist-info/WHEEL
oroio-2.0.0.dist-info/entry_points.txt
oroio-2.0.0.dist-info/top_level.txt
oroio-2.0.0.dist-info/RECORD
