Metadata-Version: 2.4
Name: oroio
Version: 2.0.0
Summary: CLI tool for oroio Factory Droid API Key Manager
Author-email: oroio Team <contact@oroio.io>
License: MIT
Project-URL: Homepage, https://github.com/notdp/oroio
Project-URL: Documentation, https://github.com/notdp/oroio/tree/main/docs
Project-URL: Repository, https://github.com/notdp/oroio
Project-URL: Issues, https://github.com/notdp/oroio/issues
Project-URL: Changelog, https://github.com/notdp/oroio/blob/main/CHANGELOG.md
Keywords: factory,api-key,droid,cli,key-manager
Classifier: Development Status :: 4 - Beta
Classifier: Intended Audience :: Developers
Classifier: License :: OSI Approved :: MIT License
Classifier: Operating System :: OS Independent
Classifier: Programming Language :: Python :: 3
Classifier: Programming Language :: Python :: 3.8
Classifier: Programming Language :: Python :: 3.9
Classifier: Programming Language :: Python :: 3.10
Classifier: Programming Language :: Python :: 3.11
Classifier: Programming Language :: Python :: 3.12
Classifier: Topic :: Software Development :: Libraries :: Python Modules
Classifier: Topic :: System :: Systems Administration
Classifier: Topic :: Utilities
Requires-Python: >=3.8
Requires-Dist: click>=8.1.7
Requires-Dist: requests>=2.31.0
Requires-Dist: rich>=13.7.0
Requires-Dist: python-dotenv>=1.0.0
Provides-Extra: dev
Requires-Dist: pytest>=7.4.0; extra == "dev"
Requires-Dist: pytest-cov>=4.1.0; extra == "dev"
Requires-Dist: black>=23.0.0; extra == "dev"
Requires-Dist: flake8>=6.0.0; extra == "dev"
Requires-Dist: mypy>=1.5.0; extra == "dev"
